text_denoising/__init__.py
text_denoising/collate_fn.py
text_denoising/utils.py
text_denoising-0.1.1.dist-info/METADATA
text_denoising-0.1.1.dist-info/WHEEL
text_denoising-0.1.1.dist-info/top_level.txt
text_denoising-0.1.1.dist-info/RECORD
