Metadata-Version: 2.1
Name: text-denoising
Version: 0.1.1
Summary: A package for text denoising : UL2
Home-page: https://github.com/your_username/text_denoising
Author: Zhi-Rui, Tam
Author-email: theblackcat102@github.io
Classifier: Programming Language :: Python :: 3
Classifier: License :: OSI Approved :: MIT License
Classifier: Operating System :: OS Independent
Requires-Python: >=3.6
Requires-Dist: numpy (>=1.18.0)
Requires-Dist: torch (>=1.7.0)
Requires-Dist: transformers
Provides-Extra: test
Requires-Dist: pytest (>=6.0.0) ; extra == 'test'
